{
  "generated_at": "2026-07-21 09:55:39",
  "market_data_time": "2026-07-21 09:55:13",
  "market_regime": {
    "model_version": "market_regime_v1",
    "state": "回避",
    "score": 5.6,
    "manual_action": "建议空仓",
    "reason": "主板上涨29.5%；强势3.0%；涨停15只/跌停87只；尾盘候选0只",
    "universe_count": 3191,
    "breadth_up_rate": 29.49,
    "breadth_strong_rate": 3.04,
    "breadth_weak_rate": 27.14,
    "limit_up_count": 15,
    "limit_down_count": 87,
    "candidate_count": 0,
    "candidate_sector_count": 0,
    "manual_decision_support_only": true
  },
  "summary": {
    "version": "human_tail_decision_v2",
    "action": "非尾盘时段",
    "candidate_code": "",
    "candidate_name": "",
    "market_state": "回避",
    "market_score": 5.6,
    "reason": "14:20后才启动尾盘人工决策辅助",
    "next_checkpoint": "下一次数据刷新后复核",
    "manual_execution_only": true,
    "order_routing_enabled": false,
    "broker_connection": "disabled"
  },
  "records": [],
  "manual_execution_only": true,
  "order_routing_enabled": false
}